dinox_client.py
dinox_api-0.3.0.dist-info/licenses/LICENSE
dinox_api-0.3.0.dist-info/METADATA
dinox_api-0.3.0.dist-info/WHEEL
dinox_api-0.3.0.dist-info/top_level.txt
dinox_api-0.3.0.dist-info/RECORD
