Metadata-Version: 2.4
Name: dinox-api
Version: 0.3.0
Summary: Python client for DinoX API - A note-taking and knowledge management system
Home-page: https://github.com/JimEverest/DinoSync
Author: JimEverest
Author-email: 
Project-URL: Homepage, https://github.com/JimEverest/DinoSync
Project-URL: Bug Reports, https://github.com/JimEverest/DinoSync/issues
Project-URL: Source, https://github.com/JimEverest/DinoSync
Project-URL: Documentation, https://github.com/JimEverest/DinoSync/blob/main/README.md
Classifier: Development Status :: 3 - Alpha
Classifier: Intended Audience :: Developers
Classifier: Topic :: Software Development :: Libraries :: Python Modules
Classifier: Topic :: Office/Business :: News/Diary
Classifier: License :: OSI Approved :: MIT License
Classifier: Programming Language :: Python :: 3
Classifier: Programming Language :: Python :: 3.7
Classifier: Programming Language :: Python :: 3.8
Classifier: Programming Language :: Python :: 3.9
Classifier: Programming Language :: Python :: 3.10
Classifier: Programming Language :: Python :: 3.11
Classifier: Operating System :: OS Independent
Requires-Python: >=3.7
License-File: LICENSE
Requires-Dist: aiohttp>=3.8.0
Requires-Dist: python-dotenv>=0.19.0
Provides-Extra: dev
Requires-Dist: pytest>=7.0.0; extra == "dev"
Requires-Dist: pytest-cov>=4.0.0; extra == "dev"
Requires-Dist: black>=22.0.0; extra == "dev"
Requires-Dist: isort>=5.0.0; extra == "dev"
Requires-Dist: flake8>=4.0.0; extra == "dev"
Dynamic: home-page
Dynamic: license-file
Dynamic: requires-python
